{
  "timestamp": "2026-04-27T17:13:37.532863+00:00",
  "stake": 0.5,
  "days_back": 90,
  "min_edge": 0.03,
  "n_historical_games": 991,
  "games_analyzed": [
    {
      "game": "TB @ CLE",
      "home": "CLE",
      "away": "TB",
      "model_probs": {
        "home_win_prob": 0.5909516572439537,
        "away_win_prob": 0.4090483427560463,
        "expected_total": 8.804018648542554,
        "over_prob": 0.4762503567853153,
        "under_prob": 0.5237496432146846,
        "home_cover_prob": 0.37269184432241326,
        "away_cover_prob": 0.6273081556775868,
        "total_line": 8.5,
        "spread_line": -2.5,
        "n_games": 50,
        "avg_similarity": 0.7687230310656119,
        "confidence": 0.5166829528835366,
        "raw_confidence": 0.4102814659746716,
        "raw_home_win_prob": 0.4245213820130093,
        "raw_over_prob": 0.4667424385631559,
        "run_distribution": {
          "1": 0.02,
          "2": 0.02,
          "3": 0.02,
          "4": 0.04,
          "5": 0.08,
          "6": 0.16,
          "7": 0.12,
          "8": 0.12,
          "9": 0.08,
          "10": 0.08,
          "11": 0.02,
          "12": 0.04,
          "13": 0.04,
          "14": 0.1,
          "15": 0.04,
          "21": 0.02
        }
      },
      "market_probs": {
        "home_win_prob": 0.5546136207799518,
        "away_win_prob": 0.44538637922004815,
        "over_prob": 0.5014331486208008,
        "under_prob": 0.4985668513791992,
        "spread_home_cover_prob": 0.3726894464363734,
        "total_line": 8.0,
        "spread_line": -1.5,
        "n_books_ml": 15,
        "n_books_total": 15
      },
      "blended_probs": {
        "home_win_prob": 0.5689796323658076,
        "away_win_prob": 0.4310203676341924,
        "over_prob": 0.4914772920452489,
        "under_prob": 0.5085227079547511,
        "home_cover_prob": 0.3726902048275686,
        "away_cover_prob": 0.4310203676341924,
        "expected_total": 8.158931829347038,
        "model_confidence": 0.5166829528835366,
        "effective_model_weight": 0.39534363944203005
      },
      "n_similar": 50,
      "n_bets": 0,
      "context_indicators": {
        "fatigue": [
          {
            "team": "CLE",
            "type": "B2B",
            "severity": "medium"
          },
          {
            "team": "TB",
            "type": "B2B",
            "severity": "medium"
          }
        ],
        "pitcher": [
          {
            "team": "CLE",
            "type": "ace",
            "value": 84.8,
            "severity": "positive"
          }
        ],
        "splits": [],
        "park": []
      },
      "pitcher_matchup": {
        "home": {
          "name": "Parker Messick",
          "era": 1.76,
          "whip": 0.88,
          "k_per_9": 8.51,
          "fip": 2.42,
          "quality_score": 84.8,
          "handedness": "L"
        },
        "away": {
          "name": "Steven Matz",
          "era": 4.81,
          "whip": 1.23,
          "k_per_9": 9.25,
          "fip": 4.95,
          "quality_score": 55.2,
          "handedness": "L"
        }
      },
      "team_splits": {
        "home": {
          "win_pct": 0.7,
          "rs_pg": 5.0,
          "ra_pg": 3.8,
          "run_diff": 1.2,
          "games": 10
        },
        "away": {
          "win_pct": 0.7,
          "rs_pg": 5.6,
          "ra_pg": 4.6,
          "run_diff": 1.0,
          "games": 10
        }
      },
      "bullpen": {
        "home": {
          "bullpen_era": 4.27,
          "bullpen_whip": 1.3,
          "bullpen_k9": 9.0,
          "bullpen_quality": 64.9,
          "team_era": 4.07
        },
        "away": {
          "bullpen_era": 4.58,
          "bullpen_whip": 1.29,
          "bullpen_k9": 7.7,
          "bullpen_quality": 59.3,
          "team_era": 4.36
        }
      },
      "park_factor": 101
    },
    {
      "game": "STL @ PIT",
      "home": "PIT",
      "away": "STL",
      "model_probs": {
        "home_win_prob": 0.4118272340051931,
        "away_win_prob": 0.588172779405852,
        "expected_total": 7.926535730056375,
        "over_prob": 0.4555156490644597,
        "under_prob": 0.5444843509355404,
        "home_cover_prob": 0.43182662110454595,
        "away_cover_prob": 0.568173378895454,
        "total_line": 8.5,
        "spread_line": -2.5,
        "n_games": 50,
        "avg_similarity": 0.7212763152944615,
        "confidence": 0.48171502824017354,
        "raw_confidence": 0.35648465883103614,
        "raw_home_win_prob": 0.5364655310589159,
        "raw_over_prob": 0.43577137587003995,
        "run_distribution": {
          "1": 0.02,
          "3": 0.02,
          "4": 0.06,
          "5": 0.1,
          "6": 0.16,
          "7": 0.2,
          "8": 0.08,
          "9": 0.08,
          "10": 0.06,
          "12": 0.04,
          "13": 0.06,
          "14": 0.02,
          "15": 0.02,
          "17": 0.04,
          "19": 0.02,
          "21": 0.02
        }
      },
      "market_probs": {
        "home_win_prob": 0.5503715812176112,
        "away_win_prob": 0.4496284187823888,
        "over_prob": 0.4950012269466805,
        "under_prob": 0.5049987730533195,
        "spread_home_cover_prob": 0.37210531651609086,
        "total_line": 8.5,
        "spread_line": -1.5,
        "n_books_ml": 15,
        "n_books_total": 15
      },
      "blended_probs": {
        "home_win_prob": 0.497484865517202,
        "away_win_prob": 0.502515134482798,
        "over_prob": 0.47992834542000495,
        "under_prob": 0.520071654579995,
        "home_cover_prob": 0.3903433101727188,
        "away_cover_prob": 0.502515134482798,
        "expected_total": 8.390545365368279,
        "model_confidence": 0.48171502824017354,
        "effective_model_weight": 0.3817313139403847
      },
      "n_similar": 50,
      "n_bets": 1,
      "context_indicators": {
        "fatigue": [
          {
            "team": "PIT",
            "type": "B2B",
            "severity": "medium"
          },
          {
            "team": "STL",
            "type": "B2B",
            "severity": "medium"
          }
        ],
        "pitcher": [],
        "splits": [],
        "park": []
      },
      "pitcher_matchup": {
        "home": {
          "name": "Mason Montgomery",
          "era": 3.97,
          "whip": 1.5,
          "k_per_9": 16.68,
          "fip": 2.13,
          "quality_score": 60.7,
          "handedness": "L"
        },
        "away": {
          "name": "Dustin May",
          "era": 5.84,
          "whip": 1.54,
          "k_per_9": 7.3,
          "fip": 3.67,
          "quality_score": 42.6,
          "handedness": "R"
        }
      },
      "team_splits": {
        "home": {
          "win_pct": 0.5,
          "rs_pg": 6.0,
          "ra_pg": 4.4,
          "run_diff": 1.6,
          "games": 10
        },
        "away": {
          "win_pct": 0.8,
          "rs_pg": 5.7,
          "ra_pg": 4.2,
          "run_diff": 1.5,
          "games": 10
        }
      },
      "bullpen": {
        "home": {
          "bullpen_era": 3.51,
          "bullpen_whip": 1.28,
          "bullpen_k9": 8.7,
          "bullpen_quality": 70.7,
          "team_era": 3.34
        },
        "away": {
          "bullpen_era": 5.11,
          "bullpen_whip": 1.47,
          "bullpen_k9": 6.4,
          "bullpen_quality": 48.7,
          "team_era": 4.87
        }
      },
      "park_factor": 99
    },
    {
      "game": "BOS @ TOR",
      "home": "TOR",
      "away": "BOS",
      "model_probs": {
        "home_win_prob": 0.4648848793888525,
        "away_win_prob": 0.5351151206111475,
        "expected_total": 9.82709508509679,
        "over_prob": 0.6156374658581392,
        "under_prob": 0.38436253414186083,
        "home_cover_prob": 0.4232495134561601,
        "away_cover_prob": 0.57675048654384,
        "total_line": 7.5,
        "spread_line": -2.5,
        "n_games": 50,
        "avg_similarity": 0.7590887297997061,
        "confidence": 0.49943618838318327,
        "raw_confidence": 0.38374798212797423,
        "raw_home_win_prob": 0.5588161896972569,
        "raw_over_prob": 0.6643746958535599,
        "run_distribution": {
          "3": 0.08,
          "4": 0.02,
          "5": 0.08,
          "6": 0.1,
          "7": 0.1,
          "8": 0.08,
          "9": 0.14,
          "10": 0.04,
          "11": 0.1,
          "12": 0.08,
          "13": 0.04,
          "14": 0.04,
          "15": 0.02,
          "16": 0.04,
          "17": 0.02,
          "20": 0.02
        }
      },
      "market_probs": {
        "home_win_prob": 0.5554836662146879,
        "away_win_prob": 0.4445163337853121,
        "over_prob": 0.49266205781869854,
        "under_prob": 0.5073379421813015,
        "spread_home_cover_prob": 0.3648478117116547,
        "total_line": 7.0,
        "spread_line": -1.5,
        "n_books_ml": 15,
        "n_books_total": 15
      },
      "blended_probs": {
        "home_win_prob": 0.5202688784357151,
        "away_win_prob": 0.4797311215642849,
        "over_prob": 0.5404612949593284,
        "under_prob": 0.4595387050406716,
        "home_cover_prob": 0.3830079094782367,
        "away_cover_prob": 0.4797311215642849,
        "expected_total": 7.549430941299706,
        "model_confidence": 0.49943618838318327,
        "effective_model_weight": 0.3886893965442239
      },
      "n_similar": 50,
      "n_bets": 1,
      "context_indicators": {
        "fatigue": [
          {
            "team": "TOR",
            "type": "B2B",
            "severity": "medium"
          },
          {
            "team": "BOS",
            "type": "B2B",
            "severity": "medium"
          }
        ],
        "pitcher": [
          {
            "team": "TOR",
            "type": "ace",
            "value": 79.4,
            "severity": "positive"
          }
        ],
        "splits": [],
        "park": []
      },
      "pitcher_matchup": {
        "home": {
          "name": "Dylan Cease",
          "era": 2.1,
          "whip": 1.29,
          "k_per_9": 15.43,
          "fip": 1.31,
          "quality_score": 79.4,
          "handedness": "R"
        },
        "away": {
          "name": "Ranger Suarez",
          "era": 4.0,
          "whip": 1.15,
          "k_per_9": 6.33,
          "fip": 4.03,
          "quality_score": 58.6,
          "handedness": "L"
        }
      },
      "team_splits": {
        "home": {
          "win_pct": 0.4,
          "rs_pg": 3.9,
          "ra_pg": 5.7,
          "run_diff": -1.8,
          "games": 10
        },
        "away": {
          "win_pct": 0.5,
          "rs_pg": 5.8,
          "ra_pg": 5.1,
          "run_diff": 0.7,
          "games": 10
        }
      },
      "bullpen": {
        "home": {
          "bullpen_era": 4.67,
          "bullpen_whip": 1.36,
          "bullpen_k9": 9.4,
          "bullpen_quality": 62.0,
          "team_era": 4.45
        },
        "away": {
          "bullpen_era": 4.6,
          "bullpen_whip": 1.38,
          "bullpen_k9": 7.8,
          "bullpen_quality": 58.1,
          "team_era": 4.38
        }
      },
      "park_factor": 99
    },
    {
      "game": "LAA @ CWS",
      "home": "CWS",
      "away": "LAA",
      "model_probs": {
        "home_win_prob": 0.37310162738537184,
        "away_win_prob": 0.6268983726146282,
        "expected_total": 9.874438114382876,
        "over_prob": 0.4860405031794963,
        "under_prob": 0.5139594968205037,
        "home_cover_prob": 0.42779326358664016,
        "away_cover_prob": 0.5722067364133598,
        "total_line": 9.0,
        "spread_line": 1.5,
        "n_games": 50,
        "avg_similarity": 0.734247663319944,
        "confidence": 0.5413113918053272,
        "raw_confidence": 0.4481713720081956,
        "raw_home_win_prob": 0.40098745306944844,
        "raw_over_prob": 0.48085822178481297,
        "run_distribution": {
          "1": 0.02,
          "2": 0.02,
          "3": 0.06,
          "4": 0.02,
          "5": 0.1,
          "6": 0.12,
          "7": 0.1,
          "8": 0.08,
          "9": 0.1,
          "11": 0.12,
          "12": 0.04,
          "14": 0.08,
          "15": 0.02,
          "16": 0.04,
          "17": 0.02,
          "18": 0.02,
          "20": 0.04
        }
      },
      "market_probs": {
        "home_win_prob": 0.48446619296193544,
        "away_win_prob": 0.5155338070380646,
        "over_prob": 0.5004851918143303,
        "under_prob": 0.49951480818566973,
        "spread_home_cover_prob": 0.6005628408553919,
        "total_line": 9.0,
        "spread_line": 1.5,
        "n_books_ml": 14,
        "n_books_total": 15
      },
      "blended_probs": {
        "home_win_prob": 0.43940182335965416,
        "away_win_prob": 0.5605981766403458,
        "over_prob": 0.49464005800484667,
        "under_prob": 0.5053599419951533,
        "home_cover_prob": 0.43940182335965416,
        "away_cover_prob": 0.4553669931686357,
        "expected_total": 9.17692343240804,
        "model_confidence": 0.5413113918053272,
        "effective_model_weight": 0.404656268975425
      },
      "n_similar": 50,
      "n_bets": 1,
      "context_indicators": {
        "fatigue": [
          {
            "team": "CWS",
            "type": "B2B",
            "severity": "medium"
          },
          {
            "team": "LAA",
            "type": "B2B",
            "severity": "medium"
          }
        ],
        "pitcher": [
          {
            "team": "CWS",
            "type": "weak",
            "value": 30.5,
            "severity": "negative"
          }
        ],
        "splits": [],
        "park": []
      },
      "pitcher_matchup": {
        "home": {
          "name": "Anthony Kay",
          "era": 5.57,
          "whip": 1.57,
          "k_per_9": 5.57,
          "fip": 6.05,
          "quality_score": 30.5,
          "handedness": "L"
        },
        "away": {
          "name": "Jack Kochanowicz",
          "era": 3.1,
          "whip": 1.24,
          "k_per_9": 5.9,
          "fip": 4.0,
          "quality_score": 56.6,
          "handedness": "R"
        }
      },
      "team_splits": {
        "home": {
          "win_pct": 0.1,
          "rs_pg": 3.2,
          "ra_pg": 5.4,
          "run_diff": -2.2,
          "games": 10
        },
        "away": {
          "win_pct": 0.4,
          "rs_pg": 6.4,
          "ra_pg": 6.4,
          "run_diff": 0.0,
          "games": 10
        }
      },
      "bullpen": {
        "home": {
          "bullpen_era": 4.9,
          "bullpen_whip": 1.48,
          "bullpen_k9": 7.5,
          "bullpen_quality": 53.2,
          "team_era": 4.67
        },
        "away": {
          "bullpen_era": 4.73,
          "bullpen_whip": 1.48,
          "bullpen_k9": 8.5,
          "bullpen_quality": 57.3,
          "team_era": 4.5
        }
      },
      "park_factor": 100
    },
    {
      "game": "SEA @ MIN",
      "home": "MIN",
      "away": "SEA",
      "model_probs": {
        "home_win_prob": 0.5082577453241381,
        "away_win_prob": 0.49174225467586197,
        "expected_total": 8.502920639653867,
        "over_prob": 0.4397102051167946,
        "under_prob": 0.5602897948832054,
        "home_cover_prob": 0.4724282597385812,
        "away_cover_prob": 0.5275717402614188,
        "total_line": 9.0,
        "spread_line": 1.5,
        "n_games": 50,
        "avg_similarity": 0.7569110555612665,
        "confidence": 0.4923382805944124,
        "raw_confidence": 0.37282812399140375,
        "raw_home_win_prob": 0.46056285529029173,
        "raw_over_prob": 0.4137646973754985,
        "run_distribution": {
          "0": 0.02,
          "1": 0.02,
          "2": 0.02,
          "3": 0.06,
          "4": 0.06,
          "5": 0.04,
          "6": 0.08,
          "7": 0.1,
          "8": 0.12,
          "9": 0.1,
          "10": 0.14,
          "11": 0.06,
          "12": 0.02,
          "14": 0.06,
          "15": 0.02,
          "16": 0.02,
          "17": 0.04,
          "19": 0.02
        }
      },
      "market_probs": {
        "home_win_prob": 0.457522137201451,
        "away_win_prob": 0.542477862798549,
        "over_prob": 0.5177126884261608,
        "under_prob": 0.4822873115738392,
        "spread_home_cover_prob": 0.5783677095321037,
        "total_line": 8.5,
        "spread_line": 1.5,
        "n_books_ml": 15,
        "n_books_total": 15
      },
      "blended_probs": {
        "home_win_prob": 0.4771018971085122,
        "away_win_prob": 0.5228981028914879,
        "over_prob": 0.48761016375239036,
        "under_prob": 0.5123898362476096,
        "home_cover_prob": 0.4771018971085122,
        "away_cover_prob": 0.45433940199599554,
        "expected_total": 8.500563563001547,
        "model_confidence": 0.4923382805944124,
        "effective_model_weight": 0.38591751693828275
      },
      "n_similar": 50,
      "n_bets": 0,
      "context_indicators": {
        "fatigue": [
          {
            "team": "MIN",
            "type": "B2B",
            "severity": "medium"
          },
          {
            "team": "SEA",
            "type": "B2B",
            "severity": "medium"
          }
        ],
        "pitcher": [
          {
            "team": "MIN",
            "type": "ace",
            "value": 73.6,
            "severity": "positive"
          }
        ],
        "splits": [],
        "park": []
      },
      "pitcher_matchup": {
        "home": {
          "name": "Connor Prielipp",
          "era": 4.5,
          "whip": 1.0,
          "k_per_9": 13.5,
          "fip": 0.1,
          "quality_score": 73.6,
          "handedness": "L"
        },
        "away": {
          "name": "Luis Castillo",
          "era": 5.01,
          "whip": 1.71,
          "k_per_9": 8.87,
          "fip": 3.4,
          "quality_score": 45.8,
          "handedness": "R"
        }
      },
      "team_splits": {
        "home": {
          "win_pct": 0.6,
          "rs_pg": 5.4,
          "ra_pg": 3.8,
          "run_diff": 1.6,
          "games": 10
        },
        "away": {
          "win_pct": 0.3,
          "rs_pg": 3.1,
          "ra_pg": 4.2,
          "run_diff": -1.1,
          "games": 10
        }
      },
      "bullpen": {
        "home": {
          "bullpen_era": 4.54,
          "bullpen_whip": 1.41,
          "bullpen_k9": 7.8,
          "bullpen_quality": 58.1,
          "team_era": 4.32
        },
        "away": {
          "bullpen_era": 3.7,
          "bullpen_whip": 1.27,
          "bullpen_k9": 7.7,
          "bullpen_quality": 66.8,
          "team_era": 3.52
        }
      },
      "park_factor": 101
    },
    {
      "game": "NYY @ TEX",
      "home": "TEX",
      "away": "NYY",
      "model_probs": {
        "home_win_prob": 0.5136200242046437,
        "away_win_prob": 0.4863799757953563,
        "expected_total": 7.386907027217019,
        "over_prob": 0.5320494991683026,
        "under_prob": 0.4679505008316974,
        "home_cover_prob": 0.5599855405479629,
        "away_cover_prob": 0.4400144594520371,
        "total_line": 8.0,
        "spread_line": 1.5,
        "n_games": 50,
        "avg_similarity": 0.6782603796701023,
        "confidence": 0.37561138150107615,
        "raw_confidence": 0.19324827923242485,
        "raw_home_win_prob": 0.6008562933294722,
        "raw_over_prob": 0.551091239175453,
        "run_distribution": {
          "1": 0.02,
          "2": 0.04,
          "3": 0.04,
          "4": 0.08,
          "5": 0.16,
          "6": 0.1,
          "7": 0.04,
          "8": 0.08,
          "9": 0.06,
          "10": 0.06,
          "11": 0.06,
          "13": 0.06,
          "15": 0.08,
          "16": 0.06,
          "18": 0.02,
          "20": 0.02,
          "22": 0.02
        }
      },
      "market_probs": {
        "home_win_prob": 0.3977121534656899,
        "away_win_prob": 0.6022878465343101,
        "over_prob": 0.5053222133162012,
        "under_prob": 0.4946777866837988,
        "spread_home_cover_prob": 0.5238905436968663,
        "total_line": 8.0,
        "spread_line": 1.5,
        "n_books_ml": 15,
        "n_books_total": 15
      },
      "blended_probs": {
        "home_win_prob": 0.43678229540716224,
        "away_win_prob": 0.5632177045928377,
        "over_prob": 0.5143314276628587,
        "under_prob": 0.48566857233714134,
        "home_cover_prob": 0.43678229540716224,
        "away_cover_prob": 0.4663759557816689,
        "expected_total": 7.896669530217243,
        "model_confidence": 0.37561138150107615,
        "effective_model_weight": 0.3370792828164845
      },
      "n_similar": 50,
      "n_bets": 0,
      "context_indicators": {
        "fatigue": [],
        "pitcher": [
          {
            "team": "NYY",
            "type": "ace",
            "value": 78.5,
            "severity": "positive"
          }
        ],
        "splits": [],
        "park": [
          {
            "team": "TEX",
            "type": "hitter-friendly",
            "value": 105,
            "severity": "medium"
          }
        ]
      },
      "pitcher_matchup": {
        "home": {
          "name": "Jack Leiter",
          "era": 4.97,
          "whip": 1.46,
          "k_per_9": 10.3,
          "fip": 3.65,
          "quality_score": 52.3,
          "handedness": "R"
        },
        "away": {
          "name": "Max Fried",
          "era": 2.4,
          "whip": 0.77,
          "k_per_9": 6.97,
          "fip": 2.59,
          "quality_score": 78.5,
          "handedness": "L"
        }
      },
      "team_splits": {
        "home": {
          "win_pct": 0.7,
          "rs_pg": 3.5,
          "ra_pg": 2.8,
          "run_diff": 0.7,
          "games": 10
        },
        "away": {
          "win_pct": 0.6,
          "rs_pg": 5.1,
          "ra_pg": 3.2,
          "run_diff": 1.9,
          "games": 10
        }
      },
      "bullpen": {
        "home": {
          "bullpen_era": 3.77,
          "bullpen_whip": 1.29,
          "bullpen_k9": 8.8,
          "bullpen_quality": 68.6,
          "team_era": 3.59
        },
        "away": {
          "bullpen_era": 3.42,
          "bullpen_whip": 1.15,
          "bullpen_k9": 8.4,
          "bullpen_quality": 72.3,
          "team_era": 3.26
        }
      },
      "park_factor": 105
    },
    {
      "game": "CHC @ SD",
      "home": "SD",
      "away": "CHC",
      "model_probs": {
        "home_win_prob": 0.6418993156567505,
        "away_win_prob": 0.3581006843432495,
        "expected_total": 7.08529132306839,
        "over_prob": 0.5586176600866793,
        "under_prob": 0.44138233991332065,
        "home_cover_prob": 0.46639312837168,
        "away_cover_prob": 0.53360687162832,
        "total_line": 7.5,
        "spread_line": -1.5,
        "n_games": 50,
        "avg_similarity": 0.7513782003649332,
        "confidence": 0.49787714538188454,
        "raw_confidence": 0.3813494544336685,
        "raw_home_win_prob": 0.5603857263052756,
        "raw_over_prob": 0.5834367840903001,
        "run_distribution": {
          "1": 0.04,
          "3": 0.02,
          "4": 0.06,
          "5": 0.08,
          "6": 0.1,
          "7": 0.2,
          "8": 0.06,
          "9": 0.12,
          "10": 0.1,
          "12": 0.04,
          "13": 0.04,
          "14": 0.06,
          "15": 0.02,
          "17": 0.02,
          "19": 0.02,
          "21": 0.02
        }
      },
      "market_probs": {
        "home_win_prob": 0.5133796721276378,
        "away_win_prob": 0.48662032787236215,
        "over_prob": 0.5051746611241833,
        "under_prob": 0.4948253388758167,
        "spread_home_cover_prob": 0.5670420025231167,
        "total_line": 7.5,
        "spread_line": 1.5,
        "n_books_ml": 15,
        "n_books_total": 15
      },
      "blended_probs": {
        "home_win_prob": 0.5632558651724164,
        "away_win_prob": 0.43674413482758356,
        "over_prob": 0.5259149406639531,
        "under_prob": 0.47408505933604694,
        "home_cover_prob": 0.5357939689054103,
        "away_cover_prob": 0.43674413482758356,
        "expected_total": 7.419529460789003,
        "model_confidence": 0.49787714538188454,
        "effective_model_weight": 0.3880822547837251
      },
      "n_similar": 50,
      "n_bets": 1,
      "context_indicators": {
        "fatigue": [],
        "pitcher": [
          {
            "team": "SD",
            "type": "ace",
            "value": 83.8,
            "severity": "positive"
          }
        ],
        "splits": [],
        "park": []
      },
      "pitcher_matchup": {
        "home": {
          "name": "Randy V\u00e1squez",
          "era": 1.88,
          "whip": 1.08,
          "k_per_9": 9.42,
          "fip": 2.3,
          "quality_score": 83.8,
          "handedness": "R"
        },
        "away": {
          "name": "Matthew Boyd",
          "era": 5.79,
          "whip": 1.14,
          "k_per_9": 14.14,
          "fip": 1.53,
          "quality_score": 60.3,
          "handedness": "L"
        }
      },
      "team_splits": {
        "home": {
          "win_pct": 0.9,
          "rs_pg": 5.8,
          "ra_pg": 3.2,
          "run_diff": 2.6,
          "games": 10
        },
        "away": {
          "win_pct": 0.7,
          "rs_pg": 7.2,
          "ra_pg": 5.1,
          "run_diff": 2.1,
          "games": 10
        }
      },
      "bullpen": {
        "home": {
          "bullpen_era": 4.16,
          "bullpen_whip": 1.33,
          "bullpen_k9": 8.6,
          "bullpen_quality": 64.4,
          "team_era": 3.96
        },
        "away": {
          "bullpen_era": 4.08,
          "bullpen_whip": 1.23,
          "bullpen_k9": 7.7,
          "bullpen_quality": 64.2,
          "team_era": 3.89
        }
      },
      "park_factor": 97
    },
    {
      "game": "MIA @ LAD",
      "home": "LAD",
      "away": "MIA",
      "model_probs": {
        "home_win_prob": 0.5629291599307564,
        "away_win_prob": 0.4370708400692436,
        "expected_total": 8.882073089299757,
        "over_prob": 0.5123939189892991,
        "under_prob": 0.4876060810107009,
        "home_cover_prob": 0.4608480489049869,
        "away_cover_prob": 0.5391519510950131,
        "total_line": 8.5,
        "spread_line": -2.5,
        "n_games": 50,
        "avg_similarity": 0.6725216699601374,
        "confidence": 0.3473107347604361,
        "raw_confidence": 0.14970882270836325,
        "raw_home_win_prob": 0.5330103556079553,
        "raw_over_prob": 0.5203217801404264,
        "run_distribution": {
          "1": 0.02,
          "3": 0.02,
          "5": 0.06,
          "6": 0.14,
          "7": 0.16,
          "8": 0.16,
          "9": 0.12,
          "10": 0.06,
          "11": 0.06,
          "12": 0.04,
          "13": 0.02,
          "14": 0.04,
          "15": 0.02,
          "17": 0.02,
          "19": 0.02,
          "20": 0.04
        }
      },
      "market_probs": {
        "home_win_prob": 0.7227790710874136,
        "away_win_prob": 0.2772209289125865,
        "over_prob": 0.4949078284425907,
        "under_prob": 0.5050921715574093,
        "spread_home_cover_prob": 0.5209776908145384,
        "total_line": 8.5,
        "spread_line": -1.5,
        "n_books_ml": 15,
        "n_books_total": 15
      },
      "blended_probs": {
        "home_win_prob": 0.6709666135321486,
        "away_win_prob": 0.3290333864678514,
        "over_prob": 0.50057562842886,
        "under_prob": 0.49942437157113995,
        "home_cover_prob": 0.5053857421086116,
        "away_cover_prob": 0.3290333864678514,
        "expected_total": 8.561921040740998,
        "model_confidence": 0.3473107347604361,
        "effective_model_weight": 0.32413191337020786
      },
      "n_similar": 50,
      "n_bets": 0,
      "context_indicators": {
        "fatigue": [],
        "pitcher": [
          {
            "team": "LAD",
            "type": "ace",
            "value": 81.4,
            "severity": "positive"
          }
        ],
        "splits": [],
        "park": []
      },
      "pitcher_matchup": {
        "home": {
          "name": "Yoshinobu Yamamoto",
          "era": 2.48,
          "whip": 0.89,
          "k_per_9": 7.71,
          "fip": 3.04,
          "quality_score": 81.4,
          "handedness": "R"
        },
        "away": {
          "name": "Chris Paddack",
          "era": 6.38,
          "whip": 1.54,
          "k_per_9": 9.38,
          "fip": 4.47,
          "quality_score": 42.1,
          "handedness": "R"
        }
      },
      "team_splits": {
        "home": {
          "win_pct": 0.8,
          "rs_pg": 5.4,
          "ra_pg": 2.9,
          "run_diff": 2.5,
          "games": 10
        },
        "away": {
          "win_pct": 0.2,
          "rs_pg": 4.0,
          "ra_pg": 5.4,
          "run_diff": -1.4,
          "games": 10
        }
      },
      "bullpen": {
        "home": {
          "bullpen_era": 3.44,
          "bullpen_whip": 1.13,
          "bullpen_k9": 8.3,
          "bullpen_quality": 72.3,
          "team_era": 3.28
        },
        "away": {
          "bullpen_era": 4.24,
          "bullpen_whip": 1.31,
          "bullpen_k9": 8.5,
          "bullpen_quality": 63.7,
          "team_era": 4.04
        }
      },
      "park_factor": 97
    }
  ],
  "recommendations": [
    {
      "game": "BOS @ TOR",
      "bet_type": "Total",
      "pick": "Over 7.5",
      "book": "espnbet",
      "odds": 115,
      "ev": 0.080995892081278,
      "roi": 0.161991784162556,
      "edge": 0.07534501588956094,
      "true_prob": 0.5404612949593284,
      "implied_prob": 0.46511627906976744,
      "american_odds": 115,
      "decimal_odds": 2.15,
      "stake": 0.5,
      "profit_if_win": 0.575,
      "loss_if_lose": 0.5,
      "is_positive_ev": true,
      "confidence": 0.49943618838318327,
      "kelly_fraction": 0.03521560525272957,
      "kelly_stake": 3.52,
      "all_book_odds": [
        {
          "book": "espnbet",
          "odds": 115,
          "point": 7.5
        },
        {
          "book": "hardrockbet",
          "odds": 115,
          "point": 7.5
        },
        {
          "book": "fliff",
          "odds": 105,
          "point": 7.5
        },
        {
          "book": "hardrockbet_oh",
          "odds": 105,
          "point": 7.5
        },
        {
          "book": "lowvig",
          "odds": -104,
          "point": 7.0
        },
        {
          "book": "betonlineag",
          "odds": -107,
          "point": 7.0
        },
        {
          "book": "betus",
          "odds": -110,
          "point": 7.0
        },
        {
          "book": "bovada",
          "odds": -110,
          "point": 7.0
        },
        {
          "book": "draftkings",
          "odds": -112,
          "point": 7.0
        },
        {
          "book": "mybookieag",
          "odds": -112,
          "point": 7.0
        },
        {
          "book": "fanduel",
          "odds": -115,
          "point": 7.0
        },
        {
          "book": "betmgm",
          "odds": -118,
          "point": 7.0
        },
        {
          "book": "ballybet",
          "odds": -120,
          "point": 7.0
        },
        {
          "book": "betparx",
          "odds": -120,
          "point": 7.0
        },
        {
          "book": "betrivers",
          "odds": -121,
          "point": 7.0
        }
      ]
    },
    {
      "game": "STL @ PIT",
      "bet_type": "Moneyline",
      "pick": "STL ML",
      "book": "betus",
      "odds": 116,
      "ev": 0.04271634524142193,
      "roi": 0.08543269048284385,
      "edge": 0.03955217151983509,
      "true_prob": 0.502515134482798,
      "implied_prob": 0.46296296296296297,
      "american_odds": 116,
      "decimal_odds": 2.16,
      "stake": 0.5,
      "profit_if_win": 0.5800000000000001,
      "loss_if_lose": 0.5,
      "is_positive_ev": true,
      "confidence": 0.48171502824017354,
      "kelly_fraction": 0.018412217776474966,
      "kelly_stake": 1.84,
      "all_book_odds": [
        {
          "book": "betus",
          "odds": 116
        },
        {
          "book": "mybookieag",
          "odds": 116
        },
        {
          "book": "lowvig",
          "odds": 116
        },
        {
          "book": "betonlineag",
          "odds": 116
        },
        {
          "book": "fliff",
          "odds": 115
        },
        {
          "book": "hardrockbet_oh",
          "odds": 115
        },
        {
          "book": "espnbet",
          "odds": 115
        },
        {
          "book": "betmgm",
          "odds": 115
        },
        {
          "book": "fanduel",
          "odds": 114
        },
        {
          "book": "draftkings",
          "odds": 113
        },
        {
          "book": "bovada",
          "odds": 113
        },
        {
          "book": "betparx",
          "odds": 112
        },
        {
          "book": "ballybet",
          "odds": 112
        },
        {
          "book": "betrivers",
          "odds": 110
        },
        {
          "book": "hardrockbet",
          "odds": 110
        }
      ]
    },
    {
      "game": "CHC @ SD",
      "bet_type": "Moneyline",
      "pick": "SD ML",
      "book": "betus",
      "odds": -109,
      "ev": 0.040002182665298314,
      "roi": 0.08000436533059663,
      "edge": 0.04172476469394759,
      "true_prob": 0.5632558651724164,
      "implied_prob": 0.5215311004784688,
      "american_odds": -109,
      "decimal_odds": 1.9174311926605505,
      "stake": 0.5,
      "profit_if_win": 0.45871559633027525,
      "loss_if_lose": 0.5,
      "is_positive_ev": true,
      "confidence": 0.49787714538188454,
      "kelly_fraction": 0.02180118955258758,
      "kelly_stake": 2.18,
      "all_book_odds": [
        {
          "book": "betus",
          "odds": -109
        },
        {
          "book": "lowvig",
          "odds": -112
        },
        {
          "book": "betonlineag",
          "odds": -112
        },
        {
          "book": "mybookieag",
          "odds": -114
        },
        {
          "book": "fliff",
          "odds": -115
        },
        {
          "book": "espnbet",
          "odds": -115
        },
        {
          "book": "hardrockbet",
          "odds": -115
        },
        {
          "book": "betmgm",
          "odds": -115
        },
        {
          "book": "fanduel",
          "odds": -116
        },
        {
          "book": "ballybet",
          "odds": -117
        },
        {
          "book": "betparx",
          "odds": -117
        },
        {
          "book": "betrivers",
          "odds": -117
        },
        {
          "book": "draftkings",
          "odds": -118
        },
        {
          "book": "hardrockbet_oh",
          "odds": -120
        },
        {
          "book": "bovada",
          "odds": -120
        }
      ]
    },
    {
      "game": "LAA @ CWS",
      "bet_type": "Moneyline",
      "pick": "LAA ML",
      "book": "betus",
      "odds": -109,
      "ev": 0.037454215219414166,
      "roi": 0.07490843043882833,
      "edge": 0.03906707616187699,
      "true_prob": 0.5605981766403458,
      "implied_prob": 0.5215311004784688,
      "american_odds": -109,
      "decimal_odds": 1.9174311926605505,
      "stake": 0.5,
      "profit_if_win": 0.45871559633027525,
      "loss_if_lose": 0.5,
      "is_positive_ev": true,
      "confidence": 0.5413113918053272,
      "kelly_fraction": 0.02041254729458072,
      "kelly_stake": 2.04,
      "all_book_odds": [
        {
          "book": "betus",
          "odds": -109
        },
        {
          "book": "lowvig",
          "odds": -111
        },
        {
          "book": "betonlineag",
          "odds": -111
        },
        {
          "book": "ballybet",
          "odds": -115
        },
        {
          "book": "betparx",
          "odds": -115
        },
        {
          "book": "bovada",
          "odds": -115
        },
        {
          "book": "fanduel",
          "odds": -116
        },
        {
          "book": "betrivers",
          "odds": -117
        },
        {
          "book": "draftkings",
          "odds": -118
        },
        {
          "book": "mybookieag",
          "odds": -118
        },
        {
          "book": "hardrockbet",
          "odds": -120
        },
        {
          "book": "hardrockbet_oh",
          "odds": -120
        },
        {
          "book": "betmgm",
          "odds": -120
        },
        {
          "book": "espnbet",
          "odds": -120
        }
      ]
    }
  ],
  "parlays": [
    {
      "legs": [
        {
          "pick": "STL ML",
          "game": "STL @ PIT",
          "odds": 116,
          "decimal_odds": 2.16,
          "true_prob": 0.502515134482798,
          "implied_prob": 0.46296296296296297,
          "edge": 0.03955217151983509,
          "bet_type": "Moneyline",
          "book": "betus"
        },
        {
          "pick": "SD ML",
          "game": "CHC @ SD",
          "odds": -109,
          "decimal_odds": 1.9174311926605505,
          "true_prob": 0.5632558651724164,
          "implied_prob": 0.5215311004784688,
          "edge": 0.04172476469394759,
          "bet_type": "Moneyline",
          "book": "betus"
        },
        {
          "pick": "Over 7.5",
          "game": "BOS @ TOR",
          "odds": 115,
          "decimal_odds": 2.15,
          "true_prob": 0.5404612949593284,
          "implied_prob": 0.46511627906976744,
          "edge": 0.07534501588956094,
          "bet_type": "Total",
          "book": "espnbet"
        }
      ],
      "n_legs": 3,
      "date": "2026-04-27",
      "datetime": "2026-04-27T17:13:37",
      "combined_odds": 790,
      "combined_decimal": 8.905,
      "combined_true_prob": 0.153,
      "combined_implied_prob": 0.1123,
      "ev": 0.1811,
      "roi": 0.3622,
      "edge": 0.0407,
      "payout": 4.45,
      "stake": 0.5
    },
    {
      "legs": [
        {
          "pick": "STL ML",
          "game": "STL @ PIT",
          "odds": 116,
          "decimal_odds": 2.16,
          "true_prob": 0.502515134482798,
          "implied_prob": 0.46296296296296297,
          "edge": 0.03955217151983509,
          "bet_type": "Moneyline",
          "book": "betus"
        },
        {
          "pick": "LAA ML",
          "game": "LAA @ CWS",
          "odds": -109,
          "decimal_odds": 1.9174311926605505,
          "true_prob": 0.5605981766403458,
          "implied_prob": 0.5215311004784688,
          "edge": 0.03906707616187699,
          "bet_type": "Moneyline",
          "book": "betus"
        },
        {
          "pick": "Over 7.5",
          "game": "BOS @ TOR",
          "odds": 115,
          "decimal_odds": 2.15,
          "true_prob": 0.5404612949593284,
          "implied_prob": 0.46511627906976744,
          "edge": 0.07534501588956094,
          "bet_type": "Total",
          "book": "espnbet"
        }
      ],
      "n_legs": 3,
      "date": "2026-04-27",
      "datetime": "2026-04-27T17:13:37",
      "combined_odds": 790,
      "combined_decimal": 8.905,
      "combined_true_prob": 0.1523,
      "combined_implied_prob": 0.1123,
      "ev": 0.1779,
      "roi": 0.3557,
      "edge": 0.04,
      "payout": 4.45,
      "stake": 0.5
    },
    {
      "legs": [
        {
          "pick": "SD ML",
          "game": "CHC @ SD",
          "odds": -109,
          "decimal_odds": 1.9174311926605505,
          "true_prob": 0.5632558651724164,
          "implied_prob": 0.5215311004784688,
          "edge": 0.04172476469394759,
          "bet_type": "Moneyline",
          "book": "betus"
        },
        {
          "pick": "LAA ML",
          "game": "LAA @ CWS",
          "odds": -109,
          "decimal_odds": 1.9174311926605505,
          "true_prob": 0.5605981766403458,
          "implied_prob": 0.5215311004784688,
          "edge": 0.03906707616187699,
          "bet_type": "Moneyline",
          "book": "betus"
        },
        {
          "pick": "Over 7.5",
          "game": "BOS @ TOR",
          "odds": 115,
          "decimal_odds": 2.15,
          "true_prob": 0.5404612949593284,
          "implied_prob": 0.46511627906976744,
          "edge": 0.07534501588956094,
          "bet_type": "Total",
          "book": "espnbet"
        }
      ],
      "n_legs": 3,
      "date": "2026-04-27",
      "datetime": "2026-04-27T17:13:37",
      "combined_odds": 690,
      "combined_decimal": 7.905,
      "combined_true_prob": 0.1707,
      "combined_implied_prob": 0.1265,
      "ev": 0.1745,
      "roi": 0.349,
      "edge": 0.0441,
      "payout": 3.95,
      "stake": 0.5
    },
    {
      "legs": [
        {
          "pick": "STL ML",
          "game": "STL @ PIT",
          "odds": 116,
          "decimal_odds": 2.16,
          "true_prob": 0.502515134482798,
          "implied_prob": 0.46296296296296297,
          "edge": 0.03955217151983509,
          "bet_type": "Moneyline",
          "book": "betus"
        },
        {
          "pick": "Over 7.5",
          "game": "BOS @ TOR",
          "odds": 115,
          "decimal_odds": 2.15,
          "true_prob": 0.5404612949593284,
          "implied_prob": 0.46511627906976744,
          "edge": 0.07534501588956094,
          "bet_type": "Total",
          "book": "espnbet"
        }
      ],
      "n_legs": 2,
      "date": "2026-04-27",
      "datetime": "2026-04-27T17:13:37",
      "combined_odds": 364,
      "combined_decimal": 4.644,
      "combined_true_prob": 0.2716,
      "combined_implied_prob": 0.2153,
      "ev": 0.1306,
      "roi": 0.2613,
      "edge": 0.0563,
      "payout": 2.32,
      "stake": 0.5
    },
    {
      "legs": [
        {
          "pick": "STL ML",
          "game": "STL @ PIT",
          "odds": 116,
          "decimal_odds": 2.16,
          "true_prob": 0.502515134482798,
          "implied_prob": 0.46296296296296297,
          "edge": 0.03955217151983509,
          "bet_type": "Moneyline",
          "book": "betus"
        },
        {
          "pick": "SD ML",
          "game": "CHC @ SD",
          "odds": -109,
          "decimal_odds": 1.9174311926605505,
          "true_prob": 0.5632558651724164,
          "implied_prob": 0.5215311004784688,
          "edge": 0.04172476469394759,
          "bet_type": "Moneyline",
          "book": "betus"
        },
        {
          "pick": "LAA ML",
          "game": "LAA @ CWS",
          "odds": -109,
          "decimal_odds": 1.9174311926605505,
          "true_prob": 0.5605981766403458,
          "implied_prob": 0.5215311004784688,
          "edge": 0.03906707616187699,
          "bet_type": "Moneyline",
          "book": "betus"
        }
      ],
      "n_legs": 3,
      "date": "2026-04-27",
      "datetime": "2026-04-27T17:13:37",
      "combined_odds": 694,
      "combined_decimal": 7.941,
      "combined_true_prob": 0.1587,
      "combined_implied_prob": 0.1259,
      "ev": 0.13,
      "roi": 0.2601,
      "edge": 0.0328,
      "payout": 3.97,
      "stake": 0.5
    },
    {
      "legs": [
        {
          "pick": "SD ML",
          "game": "CHC @ SD",
          "odds": -109,
          "decimal_odds": 1.9174311926605505,
          "true_prob": 0.5632558651724164,
          "implied_prob": 0.5215311004784688,
          "edge": 0.04172476469394759,
          "bet_type": "Moneyline",
          "book": "betus"
        },
        {
          "pick": "Over 7.5",
          "game": "BOS @ TOR",
          "odds": 115,
          "decimal_odds": 2.15,
          "true_prob": 0.5404612949593284,
          "implied_prob": 0.46511627906976744,
          "edge": 0.07534501588956094,
          "bet_type": "Total",
          "book": "espnbet"
        }
      ],
      "n_legs": 2,
      "date": "2026-04-27",
      "datetime": "2026-04-27T17:13:37",
      "combined_odds": 312,
      "combined_decimal": 4.122,
      "combined_true_prob": 0.3044,
      "combined_implied_prob": 0.2426,
      "ev": 0.1275,
      "roi": 0.255,
      "edge": 0.0618,
      "payout": 2.06,
      "stake": 0.5
    },
    {
      "legs": [
        {
          "pick": "LAA ML",
          "game": "LAA @ CWS",
          "odds": -109,
          "decimal_odds": 1.9174311926605505,
          "true_prob": 0.5605981766403458,
          "implied_prob": 0.5215311004784688,
          "edge": 0.03906707616187699,
          "bet_type": "Moneyline",
          "book": "betus"
        },
        {
          "pick": "Over 7.5",
          "game": "BOS @ TOR",
          "odds": 115,
          "decimal_odds": 2.15,
          "true_prob": 0.5404612949593284,
          "implied_prob": 0.46511627906976744,
          "edge": 0.07534501588956094,
          "bet_type": "Total",
          "book": "espnbet"
        }
      ],
      "n_legs": 2,
      "date": "2026-04-27",
      "datetime": "2026-04-27T17:13:37",
      "combined_odds": 312,
      "combined_decimal": 4.122,
      "combined_true_prob": 0.303,
      "combined_implied_prob": 0.2426,
      "ev": 0.1245,
      "roi": 0.249,
      "edge": 0.0604,
      "payout": 2.06,
      "stake": 0.5
    },
    {
      "legs": [
        {
          "pick": "STL ML",
          "game": "STL @ PIT",
          "odds": 116,
          "decimal_odds": 2.16,
          "true_prob": 0.502515134482798,
          "implied_prob": 0.46296296296296297,
          "edge": 0.03955217151983509,
          "bet_type": "Moneyline",
          "book": "betus"
        },
        {
          "pick": "SD ML",
          "game": "CHC @ SD",
          "odds": -109,
          "decimal_odds": 1.9174311926605505,
          "true_prob": 0.5632558651724164,
          "implied_prob": 0.5215311004784688,
          "edge": 0.04172476469394759,
          "bet_type": "Moneyline",
          "book": "betus"
        }
      ],
      "n_legs": 2,
      "date": "2026-04-27",
      "datetime": "2026-04-27T17:13:37",
      "combined_odds": 314,
      "combined_decimal": 4.142,
      "combined_true_prob": 0.283,
      "combined_implied_prob": 0.2414,
      "ev": 0.0861,
      "roi": 0.1723,
      "edge": 0.0416,
      "payout": 2.07,
      "stake": 0.5
    },
    {
      "legs": [
        {
          "pick": "STL ML",
          "game": "STL @ PIT",
          "odds": 116,
          "decimal_odds": 2.16,
          "true_prob": 0.502515134482798,
          "implied_prob": 0.46296296296296297,
          "edge": 0.03955217151983509,
          "bet_type": "Moneyline",
          "book": "betus"
        },
        {
          "pick": "LAA ML",
          "game": "LAA @ CWS",
          "odds": -109,
          "decimal_odds": 1.9174311926605505,
          "true_prob": 0.5605981766403458,
          "implied_prob": 0.5215311004784688,
          "edge": 0.03906707616187699,
          "bet_type": "Moneyline",
          "book": "betus"
        }
      ],
      "n_legs": 2,
      "date": "2026-04-27",
      "datetime": "2026-04-27T17:13:37",
      "combined_odds": 314,
      "combined_decimal": 4.142,
      "combined_true_prob": 0.2817,
      "combined_implied_prob": 0.2414,
      "ev": 0.0834,
      "roi": 0.1667,
      "edge": 0.0403,
      "payout": 2.07,
      "stake": 0.5
    },
    {
      "legs": [
        {
          "pick": "SD ML",
          "game": "CHC @ SD",
          "odds": -109,
          "decimal_odds": 1.9174311926605505,
          "true_prob": 0.5632558651724164,
          "implied_prob": 0.5215311004784688,
          "edge": 0.04172476469394759,
          "bet_type": "Moneyline",
          "book": "betus"
        },
        {
          "pick": "LAA ML",
          "game": "LAA @ CWS",
          "odds": -109,
          "decimal_odds": 1.9174311926605505,
          "true_prob": 0.5605981766403458,
          "implied_prob": 0.5215311004784688,
          "edge": 0.03906707616187699,
          "bet_type": "Moneyline",
          "book": "betus"
        }
      ],
      "n_legs": 2,
      "date": "2026-04-27",
      "datetime": "2026-04-27T17:13:37",
      "combined_odds": 268,
      "combined_decimal": 3.677,
      "combined_true_prob": 0.3158,
      "combined_implied_prob": 0.272,
      "ev": 0.0805,
      "roi": 0.1609,
      "edge": 0.0438,
      "payout": 1.84,
      "stake": 0.5
    }
  ],
  "quota_info": {
    "total_keys": 3,
    "total_remaining": 1116,
    "total_used": 384,
    "keys": [
      {
        "index": 0,
        "used": 384,
        "remaining": 116
      },
      {
        "index": 1,
        "used": 0,
        "remaining": 500
      },
      {
        "index": 2,
        "used": 0,
        "remaining": 500
      }
    ]
  }
}